wlgen/__init__.py
wlgen/core.py
wlgen/benchmarks/README.md
wlgen/benchmarks/__init__.py
wlgen/benchmarks/benchmark.py
wlgen/tests/__init__.py
wlgen/tests/files/sample_mixed_dos
wlgen/tests/files/sample_mixed_unix
wlgen/tests/files/tmp
wlgen-2.0.1.dist-info/METADATA
wlgen-2.0.1.dist-info/WHEEL
wlgen-2.0.1.dist-info/entry_points.txt
wlgen-2.0.1.dist-info/licenses/LICENSE.txt
wlgen-2.0.1.dist-info/RECORD
