Metadata-Version: 2.4
Name: wlgen
Version: 2.0.1
Summary: A recursive wordlist generator written in python
Author-email: tehw0lf <tehwolf@protonmail.com>
License-File: LICENSE.txt
Requires-Python: >=3.0
